server/__init__.py
server/log_decorator.py
server/server_run.py
server/common/__init__.py
server/common/descriptors.py
server/common/meta_classes.py
server/common/utils.py
server/common/variables.py
server/logs/__init__.py
server/logs/client_log_config.py
server/logs/server_log_config.py
server/server/__init__.py
server/server/add_user.py
server/server/config_window.py
server/server/core.py
server/server/main_window.py
server/server/remove_user.py
server/server/server_db.py
server/server/stat_window.py
server/unit_tests/__init__.py
server/unit_tests/test_utils.py
SuperPuper_server-0.0.1.dist-info/METADATA
SuperPuper_server-0.0.1.dist-info/WHEEL
SuperPuper_server-0.0.1.dist-info/top_level.txt
SuperPuper_server-0.0.1.dist-info/RECORD
