Metadata-Version: 2.1
Name: SuperPuper-server
Version: 0.0.1
Summary: SuperPuper_server
Home-page: UNKNOWN
Author: Roman Samarenko
Author-email: s-3m@yandex.ru
License: UNKNOWN
Platform: UNKNOWN
Requires-Dist: PyQt5
Requires-Dist: sqlalchemy
Requires-Dist: pycryptodome
Requires-Dist: pycryptodomex
